{
    "keyboard": "chonkerkeys/original",
    "keymap": "default",
    "keyboard_name": "Chonkerkeys Original",
    "layout": "LAYOUT",
    "layout_data": {
        "icons": ["0x400", "0x500", "0", "0", "0x100", "0x200", "0", "0x300"],
        "size_ordinals": ["1", "193", "0", "0", "65", "67", "0", "1"]
    },
    "layers": [
        [
            "CH_ZOOM_RAISE_HAND_TOGGLE",
            "CH_ZOOM_LEAVE_MEETING",
            "KC_NO",
            "KC_NO",
            "CH_ZOOM_MUTE_TOGGLE",
            "CH_ZOOM_VIDEO_TOGGLE",
            "KC_NO",
            "CH_ZOOM_SHARE_SCREEN_START_STOP_TOGGLE"
        ],
        [
            "CH_OPEN_APP_1",
            "CH_ZOOM_LEAVE_MEETING",
            "KC_NO",
            "KC_NO",
            "CH_ZOOM_MUTE_TOGGLE",
            "CH_ZOOM_VIDEO_TOGGLE",
            "KC_NO",
            "CH_ZOOM_SHARE_SCREEN_START_STOP_TOGGLE"
        ],
        [
            "CH_OPEN_APP_2",
            "CH_CUSTOM",
            "KC_NO",
            "KC_NO",
            "CH_CUSTOM",
            "CH_CUSTOM",
            "KC_NO",
            "CH_CUSTOM"
        ],
        [
            "CH_TEAMS_RAISE_HAND_TOGGLE",
            "CH_TEAMS_LEAVE_MEETING",
            "KC_NO",
            "KC_NO",
            "CH_TEAMS_MUTE_TOGGLE",
            "CH_TEAMS_VIDEO_TOGGLE",
            "KC_NO",
            "CH_TEAMS_SHARE_SCREEN_START_STOP_TOGGLE"
        ],
        [
            "CH_TEAMS_RAISE_HAND_TOGGLE",
            "CH_TEAMS_LEAVE_MEETING",
            "KC_NO",
            "KC_NO",
            "CH_TEAMS_MUTE_TOGGLE",
            "CH_TEAMS_VIDEO_TOGGLE",
            "KC_NO",
            "CH_TEAMS_SHARE_SCREEN_START_STOP_TOGGLE"
        ],
        [
            "CH_SKYPE_RAISE_HAND_TOGGLE",
            "CH_SKYPE_LEAVE_MEETING",
            "KC_NO",
            "KC_NO",
            "CH_SKYPE_MUTE_TOGGLE",
            "CH_SKYPE_VIDEO_TOGGLE",
            "KC_NO",
            "CH_SKYPE_SHARE_SCREEN_START_STOP_TOGGLE"
        ],
        [
            "CH_GOOGLE_MEET_RAISE_HAND_TOGGLE",
            "CH_GOOGLE_MEET_LEAVE_MEETING",
            "KC_NO",
            "KC_NO",
            "CH_GOOGLE_MEET_MUTE_TOGGLE",
            "CH_GOOGLE_MEET_VIDEO_TOGGLE",
            "KC_NO",
            "CH_GOOGLE_MEET_SHARE_SCREEN_START_STOP_TOGGLE"
        ]
    ],
    "layer_data": {
        "layer_types": ["2", "3", "1", "4", "5", "6", "8"],
        "key_off_colors": [
            [
                "0x000000FF",
                "0x000000FF",
                "0",
                "0",
                "0x110000FF",
                "0x110000FF",
                "0",
                "0xffff00FF"
            ],
            [
                "0x000000FF",
                "0x000000FF",
                "0",
                "0",
                "0x110000FF",
                "0x110000FF",
                "0",
                "0xffff00FF"
            ],
            [
                "0x000000FF",
                "0x000000FF",
                "0",
                "0",
                "0xff0000FF",
                "0xff0000FF",
                "0",
                "0xffff00FF"
            ],
            [
                "0x000000FF",
                "0x000000FF",
                "0",
                "0",
                "0x110000FF",
                "0x110000FF",
                "0",
                "0xffff00FF"
            ],
            [
                "0x000000FF",
                "0x000000FF",
                "0",
                "0",
                "0x110000FF",
                "0x110000FF",
                "0",
                "0xffff00FF"
            ],
            [
                "0x000000FF",
                "0x000000FF",
                "0",
                "0",
                "0xff0000FF",
                "0xff0000FF",
                "0",
                "0xffff00FF"
            ],
            [
                "0x000000FF",
                "0x000000FF",
                "0",
                "0",
                "0xff0000FF",
                "0xff0000FF",
                "0",
                "0xffff00FF"
            ]
        ],
        "key_on_colors": [
            [
                "0x00ff00FF",
                "0xff0000FF",
                "0",
                "0",
                "0x001100FF",
                "0x001100FF",
                "0",
                "0x001100FF"
            ],
            [
                "0x00ff00FF",
                "0xff0000FF",
                "0",
                "0",
                "0x001100FF",
                "0x001100FF",
                "0",
                "0x001100FF"
            ],
            [
                "0x00ff00FF",
                "0xff0000FF",
                "0",
                "0",
                "0x00ff00FF",
                "0x00ff00FF",
                "0",
                "0x00ff00FF"
            ],
            [
                "0x00ff00FF",
                "0xff0000FF",
                "0",
                "0",
                "0x001100FF",
                "0x001100FF",
                "0",
                "0x00ff00FF"
            ],
            [
                "0x001100FF",
                "0xff0000FF",
                "0",
                "0",
                "0x001100FF",
                "0x001100FF",
                "0",
                "0x001100FF"
            ],
            [
                "0x00ff00FF",
                "0xff0000FF",
                "0",
                "0",
                "0x00ff00FF",
                "0x00ff00FF",
                "0",
                "0x00ff00FF"
            ],
            [
                "0x00ff00FF",
                "0xff0000FF",
                "0",
                "0",
                "0x00ff00FF",
                "0x00ff00FF",
                "0",
                "0x00ff00FF"
            ]
        ],
        "key_animations": [
            [
                "RGB_STRAND_EFFECT_MOMENTARY",
                "RGB_STRAND_EFFECT_DRAINSWIRL",
                "RGB_STRAND_EFFECT_NONE",
                "RGB_STRAND_EFFECT_NONE",
                "RGB_STRAND_EFFECT_MOMENTARY",
                "RGB_STRAND_EFFECT_MOMENTARY",
                "RGB_STRAND_EFFECT_NONE",
                "RGB_STRAND_EFFECT_BLINKY"
            ],
            [
                "RGB_STRAND_EFFECT_MOMENTARY",
                "RGB_STRAND_EFFECT_DRAINSWIRL",
                "RGB_STRAND_EFFECT_NONE",
                "RGB_STRAND_EFFECT_NONE",
                "RGB_STRAND_EFFECT_MOMENTARY",
                "RGB_STRAND_EFFECT_MOMENTARY",
                "RGB_STRAND_EFFECT_NONE",
                "RGB_STRAND_EFFECT_BLINKY"
            ],
            [
                "RGB_STRAND_EFFECT_MOMENTARY",
                "RGB_STRAND_EFFECT_MOMENTARY",
                "RGB_STRAND_EFFECT_NONE",
                "RGB_STRAND_EFFECT_NONE",
                "RGB_STRAND_EFFECT_MOMENTARY",
                "RGB_STRAND_EFFECT_MOMENTARY",
                "RGB_STRAND_EFFECT_NONE",
                "RGB_STRAND_EFFECT_MOMENTARY"
            ],
            [
                "RGB_STRAND_EFFECT_MOMENTARY",
                "RGB_STRAND_EFFECT_DRAINSWIRL",
                "RGB_STRAND_EFFECT_NONE",
                "RGB_STRAND_EFFECT_NONE",
                "RGB_STRAND_EFFECT_MOMENTARY",
                "RGB_STRAND_EFFECT_MOMENTARY",
                "RGB_STRAND_EFFECT_NONE",
                "RGB_STRAND_EFFECT_BLINKY"
            ],
            [
                "RGB_STRAND_EFFECT_MOMENTARY",
                "RGB_STRAND_EFFECT_DRAINSWIRL",
                "RGB_STRAND_EFFECT_NONE",
                "RGB_STRAND_EFFECT_NONE",
                "RGB_STRAND_EFFECT_MOMENTARY",
                "RGB_STRAND_EFFECT_MOMENTARY",
                "RGB_STRAND_EFFECT_NONE",
                "RGB_STRAND_EFFECT_BLINKY"
            ],
            [
                "RGB_STRAND_EFFECT_ERROR",
                "RGB_STRAND_EFFECT_DRAINSWIRL",
                "RGB_STRAND_EFFECT_NONE",
                "RGB_STRAND_EFFECT_NONE",
                "RGB_STRAND_EFFECT_MOMENTARY",
                "RGB_STRAND_EFFECT_MOMENTARY",
                "RGB_STRAND_EFFECT_NONE",
                "RGB_STRAND_EFFECT_ERROR"
            ],
            [
                "RGB_STRAND_EFFECT_MOMENTARY",
                "RGB_STRAND_EFFECT_DRAINSWIRL",
                "RGB_STRAND_EFFECT_NONE",
                "RGB_STRAND_EFFECT_NONE",
                "RGB_STRAND_EFFECT_MOMENTARY",
                "RGB_STRAND_EFFECT_MOMENTARY",
                "RGB_STRAND_EFFECT_NONE",
                "RGB_STRAND_EFFECT_ERROR"
            ]
        ]
    },
    "layer_custom_keys": [
        [
            "KC_NO",
            "KC_NO",
            "KC_NO",
            "KC_NO",
            "KC_NO",
            "KC_NO",
            "KC_NO",
            "KC_NO",
            "KC_NO",
            "KC_NO",
            "KC_NO",
            "KC_NO",
            "KC_NO",
            "KC_NO",
            "KC_NO",
            "KC_NO",
            "KC_NO",
            "KC_NO",
            "KC_NO",
            "KC_NO",
            "KC_NO",
            "KC_NO",
            "KC_NO",
            "KC_NO"
        ],
        [
            "KC_NO",
            "KC_NO",
            "KC_NO",
            "KC_NO",
            "KC_NO",
            "KC_NO",
            "KC_NO",
            "KC_NO",
            "KC_NO",
            "KC_NO",
            "KC_NO",
            "KC_NO",
            "KC_NO",
            "KC_NO",
            "KC_NO",
            "KC_NO",
            "KC_NO",
            "KC_NO",
            "KC_NO",
            "KC_NO",
            "KC_NO",
            "KC_NO",
            "KC_NO",
            "KC_NO"
        ],
        [
            "KC_NO",
            "KC_NO",
            "KC_NO",
            "KC_NO",
            "KC_NO",
            "KC_NO",
            "KC_NO",
            "KC_NO",
            "KC_NO",
            "KC_NO",
            "KC_NO",
            "KC_NO",
            "KC_NO",
            "KC_NO",
            "KC_NO",
            "KC_NO",
            "KC_NO",
            "KC_NO",
            "KC_NO",
            "KC_NO",
            "KC_NO",
            "KC_NO",
            "KC_NO",
            "KC_NO"
        ],
        [
            "KC_NO",
            "KC_NO",
            "KC_NO",
            "KC_NO",
            "KC_NO",
            "KC_NO",
            "KC_NO",
            "KC_NO",
            "KC_NO",
            "KC_NO",
            "KC_NO",
            "KC_NO",
            "KC_NO",
            "KC_NO",
            "KC_NO",
            "KC_NO",
            "KC_NO",
            "KC_NO",
            "KC_NO",
            "KC_NO",
            "KC_NO",
            "KC_NO",
            "KC_NO",
            "KC_NO"
        ],
        [
            "KC_NO",
            "KC_NO",
            "KC_NO",
            "KC_NO",
            "KC_NO",
            "KC_NO",
            "KC_NO",
            "KC_NO",
            "KC_NO",
            "KC_NO",
            "KC_NO",
            "KC_NO",
            "KC_NO",
            "KC_NO",
            "KC_NO",
            "KC_NO",
            "KC_NO",
            "KC_NO",
            "KC_NO",
            "KC_NO",
            "KC_NO",
            "KC_NO",
            "KC_NO",
            "KC_NO"
        ],
        [
            "KC_NO",
            "KC_NO",
            "KC_NO",
            "KC_NO",
            "KC_NO",
            "KC_NO",
            "KC_NO",
            "KC_NO",
            "KC_NO",
            "KC_NO",
            "KC_NO",
            "KC_NO",
            "KC_NO",
            "KC_NO",
            "KC_NO",
            "KC_NO",
            "KC_NO",
            "KC_NO",
            "KC_NO",
            "KC_NO",
            "KC_NO",
            "KC_NO",
            "KC_NO",
            "KC_NO"
        ],
        [
            "KC_NO",
            "KC_NO",
            "KC_NO",
            "KC_NO",
            "KC_NO",
            "KC_NO",
            "KC_NO",
            "KC_NO",
            "KC_NO",
            "KC_NO",
            "KC_NO",
            "KC_NO",
            "KC_NO",
            "KC_NO",
            "KC_NO",
            "KC_NO",
            "KC_NO",
            "KC_NO",
            "KC_NO",
            "KC_NO",
            "KC_NO",
            "KC_NO",
            "KC_NO",
            "KC_NO"
        ]
    ],
    "default_locale": "0",
    "app_paths": [
        "7379548646446935855", "6014965721085062977", "8102094929534219369", "8029481832447046767", "7881708844880912752", "28719", "0", "0", "0", "0", "0", "0", "0", "0", "0", "0",
        "7526768903561293615", "7163097727371670123", "7312002113086647599", "111523881374511", "0", "0", "0", "0", "0", "0", "0", "0", "0", "0", "0", "0",
        "0", "0", "0", "0", "0", "0", "0", "0", "0", "0", "0", "0", "0", "0", "0", "0",
        "0", "0", "0", "0", "0", "0", "0", "0", "0", "0", "0", "0", "0", "0", "0", "0",
        "0", "0", "0", "0", "0", "0", "0", "0", "0", "0", "0", "0", "0", "0", "0", "0",
        "0", "0", "0", "0", "0", "0", "0", "0", "0", "0", "0", "0", "0", "0", "0", "0",
        "0", "0", "0", "0", "0", "0", "0", "0", "0", "0", "0", "0", "0", "0", "0", "0",
        "0", "0", "0", "0", "0", "0", "0", "0", "0", "0", "0", "0", "0", "0", "0", "0"
    ]
}
